CombineFiles/__init__.py
CombineFiles/main.py
CombineFiles_csv_xlsx-1.0.dist-info/LICENSE.txt
CombineFiles_csv_xlsx-1.0.dist-info/METADATA
CombineFiles_csv_xlsx-1.0.dist-info/WHEEL
CombineFiles_csv_xlsx-1.0.dist-info/top_level.txt
CombineFiles_csv_xlsx-1.0.dist-info/RECORD
