Metadata-Version: 2.1
Name: CombineFiles-csv-xlsx
Version: 1.0
Summary: Python package to combine multiple Excel and CSV files in a folder.
Author: Omkar Sutar
Author-email: Omkarsutar9702@gmail.com
Classifier: Programming Language :: Python :: 3
Classifier: License :: OSI Approved :: MIT License
Classifier: Operating System :: OS Independent
License-File: LICENSE.txt
Requires-Dist: pandas
